<?xml version="1.0" encoding="UTF-8" standalone="no"?>
<?xml-stylesheet type="text/xsl" href="style.xsl"?>
<Plot title="Average List Element Access Time">
    <Axes>
        <XAxis min="1000" max="200000">List Size</XAxis>
        <YAxis min="20.244" max="60">Microseconds</YAxis>
    </Axes>
    <Sequence title="Average Access Time vs List Size" color="red">
        <DataPoint x="1000" y="33.069"/>
        <DataPoint x="2000" y="27.842"/>
        <DataPoint x="3000" y="23.908"/>
        <DataPoint x="4000" y="26.349"/>
        <DataPoint x="5000" y="23.212"/>
        <DataPoint x="6000" y="23.765"/>
        <DataPoint x="7000" y="21.251"/>
        <DataPoint x="8000" y="21.321"/>
        <DataPoint x="9000" y="23.197"/>
        <DataPoint x="10000" y="21.527"/>
        <DataPoint x="11000" y="35.799"/>
        <DataPoint x="12000" y="22.173"/>
        <DataPoint x="197000" y="26.245"/>
        <DataPoint x="198000" y="30.013"/>
        <DataPoint x="199000" y="25.888"/>
        <DataPoint x="200000" y="23.578"/>
    </Sequence>
    <Sequence title="Access Time Distribution" color="blue">
        <DataPoint x="219" y="41.0"/>
        <DataPoint x="2839" y="38.0"/>
        <DataPoint x="5902" y="38.0"/>
        <DataPoint x="8531" y="58.0"/>
        <DataPoint x="11491" y="38.0"/>
        <DataPoint x="15415" y="38.0"/>
        <DataPoint x="17645" y="31.0"/>
        <DataPoint x="18658" y="38.0"/>
        <DataPoint x="20266" y="40.0"/>
        <DataPoint x="21854" y="31.0"/>
        <DataPoint x="197159" y="37.0"/>
        <DataPoint x="199601" y="40.0"/>
    </Sequence>
</Plot>
